src/TrafficLightController.v
module TrafficLightController(
    input wire clk,            // کلاک برای تغییر حالت‌ها
    input wire reset,          // سیگنال ریست برای بازنشانی به حالت اولیه
    input wire traffic_A,      // ترافیک در Academic Ave
    input wire traffic_B,      // ترافیک در Bravado Blvd
    output reg [1:0] LA,       // خروجی چراغ Academic (00 = قرمز، 01 = زرد، 10 = سبز)
    output reg [1:0] LB        // خروجی چراغ Bravado (00 = قرمز، 01 = زرد، 10 = سبز)
);

    // تعریف حالات به صورت مقادیر عددی
    parameter S0 = 2'b00;  // Academic: سبز، Bravado: قرمز
    parameter S1 = 2'b01;  // Academic: زرد، Bravado: قرمز
    parameter S2 = 2'b10;  // Academic: قرمز، Bravado: سبز
    parameter S3 = 2'b11;  // Academic: قرمز، Bravado: زرد

    reg [1:0] state, next_state;
    integer yellow_timer;

    // تنظیم حالت اولیه در زمان ریست
    always @(posedge clk or posedge reset) begin
        if (reset) begin
            state <= S0;
            yellow_timer <= 0;
        end else begin
            state <= next_state;
        end
    end

    // منطق انتقال حالات و تعیین خروجی چراغ‌ها
    always @(*) begin
        case (state)
            S0: begin
                LA = 2'b10; // Academic: سبز
                LB = 2'b00; // Bravado: قرمز
                if (!traffic_A)  // اگر ترافیک در Academic وجود ندارد
                    next_state = S1;
                else
                    next_state = S0;
            end
            
            S1: begin
                LA = 2'b01; // Academic: زرد
                LB = 2'b00; // Bravado: قرمز
                if (yellow_timer >= 5)  // بعد از 5 ثانیه
                    next_state = S2;
                else
                    next_state = S1;
            end
            
            S2: begin
                LA = 2'b00; // Academic: قرمز
                LB = 2'b10; // Bravado: سبز
                if (!traffic_B)  // اگر ترافیک در Bravado وجود ندارد
                    next_state = S3;
                else
                    next_state = S2;
            end
            
            S3: begin
                LA = 2'b00; // Academic: قرمز
                LB = 2'b01; // Bravado: زرد
                if (yellow_timer >= 5)  // بعد از 5 ثانیه
                    next_state = S0;
                else
                    next_state = S3;
            end
        endcase
    end

    // تایمر برای حالت‌های زرد
    always @(posedge clk) begin
        if (state == S1 || state == S3) begin
            yellow_timer <= yellow_timer + 1;
        end else begin
            yellow_timer <= 0;
        end
    end

endmodule

src/TrafficLightController_tb.v
`timescale 1ns / 1ps
`include "TrafficLightController.v"  // اطمینان از وجود ماژول TrafficLightController

module TrafficLightController_tb();

    // سیگنال‌های ورودی
    reg clk;                     // سیگنال کلاک
    reg reset;                   // سیگنال ریست
    reg traffic_A;               // سیگنال ترافیک از مسیر A
    reg traffic_B;               // سیگنال ترافیک از مسیر B
    wire [1:0] LA;               // خروجی چراغ مسیر A
    wire [1:0] LB;               // خروجی چراغ مسیر B

    // نمونه‌ای از ماژول TrafficLightController
    TrafficLightController UUT (
        .clk(clk),
        .reset(reset),
        .traffic_A(traffic_A),
        .traffic_B(traffic_B),
        .LA(LA),
        .LB(LB)
    );

    // تولید سیگنال کلاک
    initial begin
        clk = 0;
        forever #5 clk = ~clk; // کلاک با دوره 10 نانوثانیه
    end

    initial begin
        // پیکربندی برای ثبت سیگنال‌ها در GTKWave
        $dumpfile("TrafficLightController_tb.vcd");
        $dumpvars(0, TrafficLightController_tb);

        // تنظیمات اولیه
        reset = 1;               // فعال کردن ریست
        traffic_A = 0;           // ترافیک مسیر A غیرفعال
        traffic_B = 0;           // ترافیک مسیر B غیرفعال
        #10;

        reset = 0;               // غیرفعال کردن ریست
        #10;

        // سناریوی 1: ترافیک در مسیر A وجود دارد
        traffic_A = 1;           // ترافیک مسیر A فعال
        #50;                     // انتظار برای تغییر وضعیت چراغ

        // سناریوی 2: ترافیک در مسیر B وجود دارد
        traffic_A = 0;           // غیرفعال کردن ترافیک مسیر A
        traffic_B = 1;           // فعال کردن ترافیک مسیر B
        #50;                     // انتظار برای تغییر وضعیت چراغ

        // سناریوی 3: هیچ ترافیکی وجود ندارد
        traffic_B = 0;           // غیرفعال کردن ترافیک مسیر B
        #50;                     // انتظار برای تغییر وضعیت چراغ

        // پایان شبیه‌سازی
        #10 $finish;
    end

endmodule

src/TrafficLightController_tb.vcd
$date
	Mon Nov 04 22:19:38 2024
$end
$version
	Icarus Verilog
$end
$timescale
	1ps
$end
$scope module TrafficLightController_tb $end
$var wire 2 ! LB [1:0] $end
$var wire 2 " LA [1:0] $end
$var reg 1 # clk $end
$var reg 1 $ reset $end
$var reg 1 % traffic_A $end
$var reg 1 & traffic_B $end
$scope module UUT $end
$var wire 1 # clk $end
$var wire 1 $ reset $end
$var wire 1 % traffic_A $end
$var wire 1 & traffic_B $end
$var parameter 2 ' S0 $end
$var parameter 2 ( S1 $end
$var parameter 2 ) S2 $end
$var parameter 2 * S3 $end
$var reg 2 + LA [1:0] $end
$var reg 2 , LB [1:0] $end
$var reg 2 - next_state [1:0] $end
$var reg 2 . state [1:0] $end
$var integer 32 / yellow_timer [31:0] $end
$upscope $end
$upscope $end
$enddefinitions $end
$comment Show the parameter values. $end
$dumpall
b11 *
b10 )
b1 (
b0 '
$end
#0
$dumpvars
b0 /
b0 .
b1 -
b0 ,
b10 +
0&
0%
1$
0#
b10 "
b0 !
$end
#5000
1#
#10000
0#
0$
#15000
b1 "
b1 +
b1 .
1#
#20000
0#
1%
#25000
b1 /
1#
#30000
0#
#35000
b10 /
1#
#40000
0#
#45000
b11 /
1#
#50000
0#
#55000
b100 /
1#
#60000
0#
#65000
b10 -
b101 /
1#
#70000
0#
1&
0%
#75000
b10 !
b10 ,
b0 "
b0 +
b110 /
b10 .
1#
#80000
0#
#85000
b0 /
1#
#90000
0#
#95000
1#
#100000
0#
#105000
1#
#110000
0#
#115000
1#
#120000
b11 -
0#
0&
#125000
b1 !
b1 ,
b11 .
1#
#130000
0#
#135000
b1 /
1#
#140000
0#
#145000
b10 /
1#
#150000
0#
#155000
b11 /
1#
#160000
0#
#165000
b100 /
1#
#170000
0#
#175000
b0 -
b101 /
1#
